{"markdown-examples.md":"CH4L2IF-","service_php.md":"CBVUE6Ja","service_vsftpd.md":"DKGbDvrB","service_openssh.md":"Bi5iISdZ","api-examples.md":"CR35eVYZ","semi-utils.md":"Nhn6um9P","public_readme.md":"C25DNMQx","service_mysql.md":"BwzE0dWh","system_wsl.md":"DgUyBDzC","system_mac.md":"B4pjroXv","squoosh.md":"CHbKhzhi","commands.md":"CRsE_5xq","service_git.md":"BJ8fbeQU","service_ssl.md":"D65qNy--","service_harbon.md":"BLKCaue9","service_pomelo.md":"BwYhUUaV","index.md":"D5hFM8Zq","system_arch.md":"pigKPRkm"}
